{
  "AS": {
    "country": "American Samoa",
    "distance_km": 14505,
    "direction": "⬅️"
  },
  "UM": {
    "country": "United States Minor Outlying Islands",
    "distance_km": 12398,
    "direction": "⬅️"
  },
  "CK": {
    "country": "Cook Islands",
    "distance_km": 15214,
    "direction": "↙️"
  },
  "PF": {
    "country": "French Polynesia",
    "distance_km": 16325,
    "direction": "↙️"
  },
  "NU": {
    "country": "Niue",
    "distance_km": 14396,
    "direction": "↙️"
  },
  "PN": {
    "country": "Pitcairn",
    "distance_km": 16762,
    "direction": "⬇️"
  },
  "WS": {
    "country": "Samoa",
    "distance_km": 14350,
    "direction": "⬅️"
  },
  "TK": {
    "country": "Tokelau",
    "distance_km": 14549,
    "direction": "⬅️"
  },
  "TO": {
    "country": "Tonga",
    "distance_km": 13792,
    "direction": "⬅️"
  },
  "WF": {
    "country": "Wallis and Futuna",
    "distance_km": 13742,
    "direction": "⬅️"
  },
  "SV": {
    "country": "El Salvador",
    "distance_km": 15977,
    "direction": "➡️"
  },
  "GT": {
    "country": "Guatemala",
    "distance_km": 16079,
    "direction": "➡️"
  },
  "MX": {
    "country": "Mexico",
    "distance_km": 16756,
    "direction": "↗️"
  },
  "CA": {
    "country": "Canada",
    "distance_km": 13708,
    "direction": "↗️"
  },
  "AR": {
    "country": "Argentina",
    "distance_km": 12336,
    "direction": "➡️"
  },
  "FK": {
    "country": "Falkland Islands",
    "distance_km": 11221,
    "direction": "➡️"
  },
  "CL": {
    "country": "Chile",
    "distance_km": 12738,
    "direction": "↘️"
  },
  "EC": {
    "country": "Ecuador",
    "distance_km": 14851,
    "direction": "➡️"
  },
  "PE": {
    "country": "Peru",
    "distance_km": 14236,
    "direction": "➡️"
  },
  "BO": {
    "country": "Bolivia",
    "distance_km": 13001,
    "direction": "➡️"
  },
  "BR": {
    "country": "Brazil",
    "distance_km": 12049,
    "direction": "➡️"
  },
  "PY": {
    "country": "Paraguay",
    "distance_km": 12202,
    "direction": "➡️"
  },
  "UY": {
    "country": "Uruguay",
    "distance_km": 11703,
    "direction": "➡️"
  },
  "GS": {
    "country": "South Georgia and South Sandwich Islands",
    "distance_km": 9732,
    "direction": "➡️"
  },
  "AQ": {
    "country": "Antarctica",
    "distance_km": 10351,
    "direction": "↙️"
  },
  "FJ": {
    "country": "Fiji",
    "distance_km": 13234,
    "direction": "⬅️"
  },
  "SH": {
    "country": "Saint Helena",
    "distance_km": 6788,
    "direction": "➡️"
  },
  "AI": {
    "country": "Anguilla",
    "distance_km": 13180,
    "direction": "➡️"
  },
  "AG": {
    "country": "Antigua and Barbuda",
    "distance_km": 13054,
    "direction": "➡️"
  },
  "AW": {
    "country": "Aruba",
    "distance_km": 13964,
    "direction": "➡️"
  },
  "BS": {
    "country": "Bahamas",
    "distance_km": 14580,
    "direction": "➡️"
  },
  "BB": {
    "country": "Barbados",
    "distance_km": 12833,
    "direction": "➡️"
  },
  "BZ": {
    "country": "Belize",
    "distance_km": 15870,
    "direction": "➡️"
  },
  "BM": {
    "country": "Bermuda",
    "distance_km": 13106,
    "direction": "➡️"
  },
  "BQ": {
    "country": "Saint Eustatius",
    "distance_km": 13178,
    "direction": "➡️"
  },
  "VG": {
    "country": "British Virgin Islands",
    "distance_km": 13342,
    "direction": "➡️"
  },
  "KY": {
    "country": "Cayman Islands",
    "distance_km": 15053,
    "direction": "➡️"
  },
  "CO": {
    "country": "Colombia",
    "distance_km": 14264,
    "direction": "➡️"
  },
  "CR": {
    "country": "Costa Rica",
    "distance_km": 15527,
    "direction": "➡️"
  },
  "CU": {
    "country": "Cuba",
    "distance_km": 14837,
    "direction": "➡️"
  },
  "CW": {
    "country": "Curacao",
    "distance_km": 13857,
    "direction": "➡️"
  },
  "DM": {
    "country": "Dominica",
    "distance_km": 13019,
    "direction": "➡️"
  },
  "DO": {
    "country": "Dominican Republic",
    "distance_km": 13946,
    "direction": "➡️"
  },
  "GF": {
    "country": "French Guiana",
    "distance_km": 12122,
    "direction": "➡️"
  },
  "GD": {
    "country": "Grenada",
    "distance_km": 13066,
    "direction": "➡️"
  },
  "GP": {
    "country": "Guadeloupe",
    "distance_km": 13034,
    "direction": "➡️"
  },
  "GY": {
    "country": "Guyana",
    "distance_km": 12746,
    "direction": "➡️"
  },
  "HT": {
    "country": "Haiti",
    "distance_km": 14200,
    "direction": "➡️"
  },
  "HN": {
    "country": "Honduras",
    "distance_km": 15706,
    "direction": "➡️"
  },
  "JM": {
    "country": "Jamaica",
    "distance_km": 14673,
    "direction": "➡️"
  },
  "MQ": {
    "country": "Martinique",
    "distance_km": 12986,
    "direction": "➡️"
  },
  "MS": {
    "country": "Montserrat",
    "distance_km": 13099,
    "direction": "➡️"
  },
  "NI": {
    "country": "Nicaragua",
    "distance_km": 15584,
    "direction": "➡️"
  },
  "PA": {
    "country": "Panama",
    "distance_km": 15097,
    "direction": "➡️"
  },
  "PR": {
    "country": "Puerto Rico",
    "distance_km": 13541,
    "direction": "➡️"
  },
  "BL": {
    "country": "Saint Barthelemy",
    "distance_km": 13158,
    "direction": "➡️"
  },
  "KN": {
    "country": "Saint Kitts and Nevis",
    "distance_km": 13154,
    "direction": "➡️"
  },
  "LC": {
    "country": "Saint Lucia",
    "distance_km": 12984,
    "direction": "➡️"
  },
  "MF": {
    "country": "Saint Martin",
    "distance_km": 13182,
    "direction": "➡️"
  },
  "PM": {
    "country": "Saint Pierre and Miquelon",
    "distance_km": 12029,
    "direction": "➡️"
  },
  "VC": {
    "country": "Saint Vincent and the Grenadines",
    "distance_km": 13010,
    "direction": "➡️"
  },
  "SX": {
    "country": "Sint Maarten",
    "distance_km": 13182,
    "direction": "➡️"
  },
  "SR": {
    "country": "Suriname",
    "distance_km": 12404,
    "direction": "➡️"
  },
  "TT": {
    "country": "Trinidad and Tobago",
    "distance_km": 13034,
    "direction": "➡️"
  },
  "TC": {
    "country": "Turks and Caicos Islands",
    "distance_km": 14027,
    "direction": "➡️"
  },
  "VI": {
    "country": "US Virgin Islands",
    "distance_km": 13364,
    "direction": "➡️"
  },
  "VE": {
    "country": "Venezuela",
    "distance_km": 13580,
    "direction": "➡️"
  },
  "BF": {
    "country": "Burkina Faso",
    "distance_km": 6588,
    "direction": "➡️"
  },
  "CV": {
    "country": "Cabo Verde",
    "distance_km": 8979,
    "direction": "➡️"
  },
  "CI": {
    "country": "Côte d'Ivoire",
    "distance_km": 6907,
    "direction": "➡️"
  },
  "GM": {
    "country": "Gambia",
    "distance_km": 8073,
    "direction": "➡️"
  },
  "GH": {
    "country": "Ghana",
    "distance_km": 6442,
    "direction": "➡️"
  },
  "GI": {
    "country": "Gibraltar",
    "distance_km": 7767,
    "direction": "➡️"
  },
  "GN": {
    "country": "Guinea",
    "distance_km": 7543,
    "direction": "➡️"
  },
  "GW": {
    "country": "Guinea-Bissau",
    "distance_km": 8004,
    "direction": "➡️"
  },
  "LR": {
    "country": "Liberia",
    "distance_km": 7292,
    "direction": "➡️"
  },
  "ML": {
    "country": "Mali",
    "distance_km": 7000,
    "direction": "➡️"
  },
  "MR": {
    "country": "Mauritania",
    "distance_km": 7717,
    "direction": "➡️"
  },
  "MA": {
    "country": "Morocco",
    "distance_km": 7795,
    "direction": "➡️"
  },
  "PT": {
    "country": "Portugal",
    "distance_km": 8123,
    "direction": "➡️"
  },
  "SN": {
    "country": "Senegal",
    "distance_km": 8005,
    "direction": "➡️"
  },
  "SL": {
    "country": "Sierra Leone",
    "distance_km": 7600,
    "direction": "➡️"
  },
  "GL": {
    "country": "Greenland",
    "distance_km": 10735,
    "direction": "➡️"
  },
  "GG": {
    "country": "Guernsey",
    "distance_km": 8192,
    "direction": "↘️"
  },
  "IE": {
    "country": "Ireland",
    "distance_km": 8734,
    "direction": "↘️"
  },
  "IM": {
    "country": "Isle of Man",
    "distance_km": 8559,
    "direction": "↘️"
  },
  "JE": {
    "country": "Jersey",
    "distance_km": 8151,
    "direction": "↘️"
  },
  "GB": {
    "country": "United Kingdom",
    "distance_km": 8450,
    "direction": "↘️"
  },
  "IS": {
    "country": "Iceland",
    "distance_km": 9765,
    "direction": "➡️"
  },
  "FO": {
    "country": "Faroe Islands",
    "distance_km": 9089,
    "direction": "↘️"
  },
  "SJ": {
    "country": "Svalbard",
    "distance_km": 9543,
    "direction": "↘️"
  },
  "BV": {
    "country": "Bouvet Island",
    "distance_km": 7228,
    "direction": "↗️"
  },
  "NZ": {
    "country": "New Zealand",
    "distance_km": 11618,
    "direction": "⬅️"
  },
  "AO": {
    "country": "Angola",
    "distance_km": 4238,
    "direction": "➡️"
  },
  "BW": {
    "country": "Botswana",
    "distance_km": 3922,
    "direction": "↗️"
  },
  "BI": {
    "country": "Burundi",
    "distance_km": 2842,
    "direction": "➡️"
  },
  "KM": {
    "country": "Comoros",
    "distance_km": 1544,
    "direction": "↗️"
  },
  "CG": {
    "country": "Congo",
    "distance_km": 4529,
    "direction": "➡️"
  },
  "CD": {
    "country": "Congo DRC",
    "distance_km": 3558,
    "direction": "➡️"
  },
  "GA": {
    "country": "Gabon",
    "distance_km": 4866,
    "direction": "➡️"
  },
  "KE": {
    "country": "Kenya",
    "distance_km": 2035,
    "direction": "➡️"
  },
  "LS": {
    "country": "Lesotho",
    "distance_km": 3985,
    "direction": "↗️"
  },
  "MW": {
    "country": "Malawi",
    "distance_km": 2514,
    "direction": "➡️"
  },
  "TF": {
    "country": "Glorioso Islands",
    "distance_km": 1183,
    "direction": "↗️"
  },
  "MZ": {
    "country": "Mozambique",
    "distance_km": 2629,
    "direction": "↗️"
  },
  "NA": {
    "country": "Namibia",
    "distance_km": 4450,
    "direction": "➡️"
  },
  "RW": {
    "country": "Rwanda",
    "distance_km": 2851,
    "direction": "➡️"
  },
  "ST": {
    "country": "Sao Tome and Principe",
    "distance_km": 5455,
    "direction": "➡️"
  },
  "ZA": {
    "country": "South Africa",
    "distance_km": 4190,
    "direction": "↗️"
  },
  "SZ": {
    "country": "Eswatini",
    "distance_km": 3523,
    "direction": "↗️"
  },
  "TZ": {
    "country": "Tanzania",
    "distance_km": 2294,
    "direction": "➡️"
  },
  "ZM": {
    "country": "Zambia",
    "distance_km": 3185,
    "direction": "➡️"
  },
  "ZW": {
    "country": "Zimbabwe",
    "distance_km": 3213,
    "direction": "↗️"
  },
  "IO": {
    "country": "British Indian Ocean Territory",
    "distance_km": 1899,
    "direction": "⬅️"
  },
  "HM": {
    "country": "Heard Island and McDonald Islands",
    "distance_km": 5630,
    "direction": "↖️"
  },
  "MG": {
    "country": "Madagascar",
    "distance_km": 1862,
    "direction": "↗️"
  },
  "MU": {
    "country": "Mauritius",
    "distance_km": 1752,
    "direction": "⬆️"
  },
  "YT": {
    "country": "Mayotte",
    "distance_km": 1454,
    "direction": "↗️"
  },
  "RE": {
    "country": "Réunion",
    "distance_km": 1830,
    "direction": "⬆️"
  },
  "DZ": {
    "country": "Algeria",
    "distance_km": 6734,
    "direction": "↘️"
  },
  "BJ": {
    "country": "Benin",
    "distance_km": 6098,
    "direction": "➡️"
  },
  "CM": {
    "country": "Cameroon",
    "distance_km": 4875,
    "direction": "➡️"
  },
  "CF": {
    "country": "Central African Republic",
    "distance_km": 4068,
    "direction": "➡️"
  },
  "TD": {
    "country": "Chad",
    "distance_km": 4643,
    "direction": "↘️"
  },
  "GQ": {
    "country": "Equatorial Guinea",
    "distance_km": 5053,
    "direction": "➡️"
  },
  "KI": {
    "country": "Kiribati",
    "distance_km": 16354,
    "direction": "⬅️"
  },
  "LY": {
    "country": "Libya",
    "distance_km": 5368,
    "direction": "↘️"
  },
  "MT": {
    "country": "Malta",
    "distance_km": 6209,
    "direction": "↘️"
  },
  "NE": {
    "country": "Niger",
    "distance_km": 5660,
    "direction": "➡️"
  },
  "NG": {
    "country": "Nigeria",
    "distance_km": 5478,
    "direction": "➡️"
  },
  "TG": {
    "country": "Togo",
    "distance_km": 6229,
    "direction": "➡️"
  },
  "TN": {
    "country": "Tunisia",
    "distance_km": 6450,
    "direction": "↘️"
  },
  "CY": {
    "country": "Cyprus",
    "distance_km": 4990,
    "direction": "↘️"
  },
  "DJ": {
    "country": "Djibouti",
    "distance_km": 2313,
    "direction": "↘️"
  },
  "EG": {
    "country": "Egypt",
    "distance_km": 4411,
    "direction": "↘️"
  },
  "ER": {
    "country": "Eritrea",
    "distance_km": 2823,
    "direction": "↘️"
  },
  "ET": {
    "country": "Ethiopia",
    "distance_km": 2279,
    "direction": "↘️"
  },
  "GR": {
    "country": "Greece",
    "distance_km": 5918,
    "direction": "↘️"
  },
  "IQ": {
    "country": "Iraq",
    "distance_km": 4375,
    "direction": "⬇️"
  },
  "IL": {
    "country": "Israel",
    "distance_km": 4569,
    "direction": "↘️"
  },
  "JO": {
    "country": "Jordan",
    "distance_km": 4463,
    "direction": "↘️"
  },
  "LB": {
    "country": "Lebanon",
    "distance_km": 4756,
    "direction": "↘️"
  },
  "PS": {
    "country": "Palestinian Territory",
    "distance_km": 4597,
    "direction": "↘️"
  },
  "SS": {
    "country": "South Sudan",
    "distance_km": 3102,
    "direction": "↘️"
  },
  "SD": {
    "country": "Sudan",
    "distance_km": 3606,
    "direction": "↘️"
  },
  "SY": {
    "country": "Syria",
    "distance_km": 4763,
    "direction": "↘️"
  },
  "TR": {
    "country": "Turkey",
    "distance_km": 5261,
    "direction": "↘️"
  },
  "UG": {
    "country": "Uganda",
    "distance_km": 2653,
    "direction": "➡️"
  },
  "AD": {
    "country": "Andorra",
    "distance_km": 7539,
    "direction": "↘️"
  },
  "US": {
    "country": "United States",
    "distance_km": 15271,
    "direction": "↗️"
  },
  "FR": {
    "country": "France",
    "distance_km": 7729,
    "direction": "↘️"
  },
  "LI": {
    "country": "Liechtenstein",
    "distance_km": 7302,
    "direction": "↘️"
  },
  "MC": {
    "country": "Monaco",
    "distance_km": 7211,
    "direction": "↘️"
  },
  "CH": {
    "country": "Switzerland",
    "distance_km": 7350,
    "direction": "↘️"
  },
  "BE": {
    "country": "Belgium",
    "distance_km": 7818,
    "direction": "↘️"
  },
  "DE": {
    "country": "Germany",
    "distance_km": 7530,
    "direction": "↘️"
  },
  "LU": {
    "country": "Luxembourg",
    "distance_km": 7681,
    "direction": "↘️"
  },
  "NL": {
    "country": "Netherlands",
    "distance_km": 7866,
    "direction": "↘️"
  },
  "AL": {
    "country": "Albania",
    "distance_km": 6234,
    "direction": "↘️"
  },
  "AT": {
    "country": "Austria",
    "distance_km": 7093,
    "direction": "↘️"
  },
  "BA": {
    "country": "Bosnia and Herzegovina",
    "distance_km": 6599,
    "direction": "↘️"
  },
  "HR": {
    "country": "Croatia",
    "distance_km": 6728,
    "direction": "↘️"
  },
  "CZ": {
    "country": "Czech Republic",
    "distance_km": 7171,
    "direction": "↘️"
  },
  "DK": {
    "country": "Denmark",
    "distance_km": 7938,
    "direction": "↘️"
  },
  "HU": {
    "country": "Hungary",
    "distance_km": 6764,
    "direction": "↘️"
  },
  "IT": {
    "country": "Italy",
    "distance_km": 6815,
    "direction": "↘️"
  },
  "ME": {
    "country": "Montenegro",
    "distance_km": 6405,
    "direction": "↘️"
  },
  "PL": {
    "country": "Poland",
    "distance_km": 7166,
    "direction": "↘️"
  },
  "SM": {
    "country": "San Marino",
    "distance_km": 6902,
    "direction": "↘️"
  },
  "RS": {
    "country": "Serbia",
    "distance_km": 6424,
    "direction": "↘️"
  },
  "SK": {
    "country": "Slovakia",
    "distance_km": 6877,
    "direction": "↘️"
  },
  "SI": {
    "country": "Slovenia",
    "distance_km": 6919,
    "direction": "↘️"
  },
  "MK": {
    "country": "North Macedonia",
    "distance_km": 6176,
    "direction": "↘️"
  },
  "VA": {
    "country": "Vatican City",
    "distance_km": 6759,
    "direction": "↘️"
  },
  "NO": {
    "country": "Norway",
    "distance_km": 8365,
    "direction": "↘️"
  },
  "SE": {
    "country": "Sweden",
    "distance_km": 8162,
    "direction": "↘️"
  },
  "BY": {
    "country": "Belarus",
    "distance_km": 6955,
    "direction": "↘️"
  },
  "BG": {
    "country": "Bulgaria",
    "distance_km": 6093,
    "direction": "↘️"
  },
  "EE": {
    "country": "Estonia",
    "distance_km": 7512,
    "direction": "↘️"
  },
  "FI": {
    "country": "Finland",
    "distance_km": 8122,
    "direction": "↘️"
  },
  "GE": {
    "country": "Georgia",
    "distance_km": 5350,
    "direction": "⬇️"
  },
  "LV": {
    "country": "Latvia",
    "distance_km": 7381,
    "direction": "↘️"
  },
  "LT": {
    "country": "Lithuania",
    "distance_km": 7268,
    "direction": "↘️"
  },
  "MD": {
    "country": "Moldova",
    "distance_km": 6336,
    "direction": "↘️"
  },
  "RO": {
    "country": "Romania",
    "distance_km": 6366,
    "direction": "↘️"
  },
  "UA": {
    "country": "Ukraine",
    "distance_km": 6377,
    "direction": "↘️"
  },
  "AF": {
    "country": "Afghanistan",
    "distance_km": 4469,
    "direction": "⬇️"
  },
  "BH": {
    "country": "Bahrain",
    "distance_km": 3456,
    "direction": "⬇️"
  },
  "IN": {
    "country": "India",
    "distance_km": 4199,
    "direction": "↙️"
  },
  "IR": {
    "country": "Iran",
    "distance_km": 4179,
    "direction": "⬇️"
  },
  "KW": {
    "country": "Kuwait",
    "distance_km": 3867,
    "direction": "⬇️"
  },
  "MV": {
    "country": "Maldives",
    "distance_km": 2009,
    "direction": "⬅️"
  },
  "NP": {
    "country": "Nepal",
    "distance_km": 4780,
    "direction": "↙️"
  },
  "OM": {
    "country": "Oman",
    "distance_km": 2823,
    "direction": "⬇️"
  },
  "PK": {
    "country": "Pakistan",
    "distance_km": 4130,
    "direction": "↙️"
  },
  "QA": {
    "country": "Qatar",
    "distance_km": 3365,
    "direction": "⬇️"
  },
  "SA": {
    "country": "Saudi Arabia",
    "distance_km": 3412,
    "direction": "⬇️"
  },
  "SO": {
    "country": "Somalia",
    "distance_km": 1672,
    "direction": "↘️"
  },
  "LK": {
    "country": "Sri Lanka",
    "distance_km": 3115,
    "direction": "↙️"
  },
  "TJ": {
    "country": "Tajikistan",
    "distance_km": 5064,
    "direction": "⬇️"
  },
  "TM": {
    "country": "Turkmenistan",
    "distance_km": 4871,
    "direction": "⬇️"
  },
  "AE": {
    "country": "United Arab Emirates",
    "distance_km": 3210,
    "direction": "⬇️"
  },
  "YE": {
    "country": "Yemen",
    "distance_km": 2460,
    "direction": "⬇️"
  },
  "AM": {
    "country": "Armenia",
    "distance_km": 5098,
    "direction": "⬇️"
  },
  "AZ": {
    "country": "Azerbaijan",
    "distance_km": 5058,
    "direction": "⬇️"
  },
  "KZ": {
    "country": "Kazakhstan",
    "distance_km": 5913,
    "direction": "⬇️"
  },
  "KG": {
    "country": "Kyrgyzstan",
    "distance_km": 5458,
    "direction": "↙️"
  },
  "UZ": {
    "country": "Uzbekistan",
    "distance_km": 5202,
    "direction": "⬇️"
  },
  "CX": {
    "country": "Christmas Island",
    "distance_km": 5568,
    "direction": "⬅️"
  },
  "CC": {
    "country": "Cocos Islands",
    "distance_km": 4620,
    "direction": "⬅️"
  },
  "ID": {
    "country": "Indonesia",
    "distance_km": 6519,
    "direction": "⬅️"
  },
  "TL": {
    "country": "Timor-Leste",
    "distance_km": 7787,
    "direction": "⬅️"
  },
  "AU": {
    "country": "Australia",
    "distance_km": 8637,
    "direction": "⬅️"
  },
  "NR": {
    "country": "Nauru",
    "distance_km": 12380,
    "direction": "⬅️"
  },
  "NC": {
    "country": "New Caledonia",
    "distance_km": 11872,
    "direction": "⬅️"
  },
  "NF": {
    "country": "Norfolk Island",
    "distance_km": 11907,
    "direction": "⬅️"
  },
  "PG": {
    "country": "Papua New Guinea",
    "distance_km": 9873,
    "direction": "⬅️"
  },
  "SB": {
    "country": "Solomon Islands",
    "distance_km": 11523,
    "direction": "⬅️"
  },
  "TV": {
    "country": "Tuvalu",
    "distance_km": 13608,
    "direction": "⬅️"
  },
  "VU": {
    "country": "Vanuatu",
    "distance_km": 12146,
    "direction": "⬅️"
  },
  "KH": {
    "country": "Cambodia",
    "distance_km": 5806,
    "direction": "⬅️"
  },
  "LA": {
    "country": "Laos",
    "distance_km": 5868,
    "direction": "⬅️"
  },
  "MY": {
    "country": "Malaysia",
    "distance_km": 6637,
    "direction": "⬅️"
  },
  "MM": {
    "country": "Myanmar",
    "distance_km": 5304,
    "direction": "↙️"
  },
  "SG": {
    "country": "Singapore",
    "distance_km": 5411,
    "direction": "⬅️"
  },
  "TH": {
    "country": "Thailand",
    "distance_km": 5430,
    "direction": "⬅️"
  },
  "VN": {
    "country": "Vietnam",
    "distance_km": 6023,
    "direction": "⬅️"
  },
  "BD": {
    "country": "Bangladesh",
    "distance_km": 4928,
    "direction": "↙️"
  },
  "BT": {
    "country": "Bhutan",
    "distance_km": 5179,
    "direction": "↙️"
  },
  "CN": {
    "country": "China",
    "distance_km": 6945,
    "direction": "↙️"
  },
  "BN": {
    "country": "Brunei Darussalam",
    "distance_km": 6651,
    "direction": "⬅️"
  },
  "PH": {
    "country": "Philippines",
    "distance_km": 7639,
    "direction": "⬅️"
  },
  "KR": {
    "country": "South Korea",
    "distance_km": 8752,
    "direction": "⬅️"
  },
  "MN": {
    "country": "Mongolia",
    "distance_km": 7419,
    "direction": "↙️"
  },
  "KP": {
    "country": "North Korea",
    "distance_km": 8825,
    "direction": "⬅️"
  },
  "GU": {
    "country": "Guam",
    "distance_km": 10053,
    "direction": "⬅️"
  },
  "JP": {
    "country": "Japan",
    "distance_km": 9609,
    "direction": "⬅️"
  },
  "MH": {
    "country": "Marshall Islands",
    "distance_km": 12633,
    "direction": "⬅️"
  },
  "FM": {
    "country": "Micronesia",
    "distance_km": 11475,
    "direction": "⬅️"
  },
  "MP": {
    "country": "Northern Mariana Islands",
    "distance_km": 10172,
    "direction": "⬅️"
  },
  "PW": {
    "country": "Palau",
    "distance_km": 8880,
    "direction": "⬅️"
  },
  "RU": {
    "country": "Russian Federation",
    "distance_km": 8039,
    "direction": "↙️"
  },
  "ES": {
    "country": "Canarias",
    "distance_km": 8512,
    "direction": "➡️"
  }
}