{
  "AS": {
    "country": "American Samoa",
    "distance_km": 1273,
    "direction": "↖️"
  },
  "UM": {
    "country": "United States Minor Outlying Islands",
    "distance_km": 3386,
    "direction": "↘️"
  },
  "CK": {
    "country": "Cook Islands",
    "distance_km": 2657,
    "direction": "↖️"
  },
  "PF": {
    "country": "French Polynesia",
    "distance_km": 3542,
    "direction": "⬅️"
  },
  "NU": {
    "country": "Niue",
    "distance_km": 1660,
    "direction": "↖️"
  },
  "PN": {
    "country": "Pitcairn",
    "distance_km": 5828,
    "direction": "⬅️"
  },
  "WS": {
    "country": "Samoa",
    "distance_km": 1073,
    "direction": "↖️"
  },
  "TK": {
    "country": "Tokelau",
    "distance_km": 984,
    "direction": "⬅️"
  },
  "TO": {
    "country": "Tonga",
    "distance_km": 1528,
    "direction": "↖️"
  },
  "WF": {
    "country": "Wallis and Futuna",
    "distance_km": 704,
    "direction": "↖️"
  },
  "SV": {
    "country": "El Salvador",
    "distance_km": 10438,
    "direction": "⬅️"
  },
  "GT": {
    "country": "Guatemala",
    "distance_km": 10315,
    "direction": "⬅️"
  },
  "MX": {
    "country": "Mexico",
    "distance_km": 9311,
    "direction": "⬅️"
  },
  "CA": {
    "country": "Canada",
    "distance_km": 10355,
    "direction": "⬅️"
  },
  "AR": {
    "country": "Argentina",
    "distance_km": 11742,
    "direction": "↙️"
  },
  "FK": {
    "country": "Falkland Islands",
    "distance_km": 11345,
    "direction": "↙️"
  },
  "CL": {
    "country": "Chile",
    "distance_km": 11138,
    "direction": "⬅️"
  },
  "EC": {
    "country": "Ecuador",
    "distance_km": 11335,
    "direction": "⬅️"
  },
  "PE": {
    "country": "Peru",
    "distance_km": 11674,
    "direction": "⬅️"
  },
  "BO": {
    "country": "Bolivia",
    "distance_km": 12473,
    "direction": "⬅️"
  },
  "BR": {
    "country": "Brazil",
    "distance_km": 13686,
    "direction": "⬅️"
  },
  "PY": {
    "country": "Paraguay",
    "distance_km": 12820,
    "direction": "↙️"
  },
  "UY": {
    "country": "Uruguay",
    "distance_km": 12587,
    "direction": "↙️"
  },
  "GS": {
    "country": "South Georgia and South Sandwich Islands",
    "distance_km": 12256,
    "direction": "↙️"
  },
  "AQ": {
    "country": "Antarctica",
    "distance_km": 7636,
    "direction": "⬆️"
  },
  "FJ": {
    "country": "Fiji",
    "distance_km": 1044,
    "direction": "⬆️"
  },
  "SH": {
    "country": "Saint Helena",
    "distance_km": 17240,
    "direction": "⬇️"
  },
  "AI": {
    "country": "Anguilla",
    "distance_km": 13221,
    "direction": "⬅️"
  },
  "AG": {
    "country": "Antigua and Barbuda",
    "distance_km": 13356,
    "direction": "⬅️"
  },
  "AW": {
    "country": "Aruba",
    "distance_km": 12457,
    "direction": "⬅️"
  },
  "BS": {
    "country": "Bahamas",
    "distance_km": 11680,
    "direction": "⬅️"
  },
  "BB": {
    "country": "Barbados",
    "distance_km": 13588,
    "direction": "⬅️"
  },
  "BZ": {
    "country": "Belize",
    "distance_km": 10508,
    "direction": "⬅️"
  },
  "BM": {
    "country": "Bermuda",
    "distance_km": 12953,
    "direction": "⬅️"
  },
  "BQ": {
    "country": "Saint Eustatius",
    "distance_km": 13230,
    "direction": "⬅️"
  },
  "VG": {
    "country": "British Virgin Islands",
    "distance_km": 13056,
    "direction": "⬅️"
  },
  "KY": {
    "country": "Cayman Islands",
    "distance_km": 11313,
    "direction": "⬅️"
  },
  "CO": {
    "country": "Colombia",
    "distance_km": 12068,
    "direction": "⬅️"
  },
  "CR": {
    "country": "Costa Rica",
    "distance_km": 10889,
    "direction": "⬅️"
  },
  "CU": {
    "country": "Cuba",
    "distance_km": 11494,
    "direction": "⬅️"
  },
  "CW": {
    "country": "Curacao",
    "distance_km": 12563,
    "direction": "⬅️"
  },
  "DM": {
    "country": "Dominica",
    "distance_km": 13400,
    "direction": "⬅️"
  },
  "DO": {
    "country": "Dominican Republic",
    "distance_km": 12444,
    "direction": "⬅️"
  },
  "GF": {
    "country": "French Guiana",
    "distance_km": 14188,
    "direction": "⬅️"
  },
  "GD": {
    "country": "Grenada",
    "distance_km": 13354,
    "direction": "⬅️"
  },
  "GP": {
    "country": "Guadeloupe",
    "distance_km": 13382,
    "direction": "⬅️"
  },
  "GY": {
    "country": "Guyana",
    "distance_km": 13585,
    "direction": "⬅️"
  },
  "HT": {
    "country": "Haiti",
    "distance_km": 12186,
    "direction": "⬅️"
  },
  "HN": {
    "country": "Honduras",
    "distance_km": 10705,
    "direction": "⬅️"
  },
  "JM": {
    "country": "Jamaica",
    "distance_km": 11717,
    "direction": "⬅️"
  },
  "MQ": {
    "country": "Martinique",
    "distance_km": 13436,
    "direction": "⬅️"
  },
  "MS": {
    "country": "Montserrat",
    "distance_km": 13313,
    "direction": "⬅️"
  },
  "NI": {
    "country": "Nicaragua",
    "distance_km": 10837,
    "direction": "⬅️"
  },
  "PA": {
    "country": "Panama",
    "distance_km": 11305,
    "direction": "⬅️"
  },
  "PR": {
    "country": "Puerto Rico",
    "distance_km": 12858,
    "direction": "⬅️"
  },
  "BL": {
    "country": "Saint Barthelemy",
    "distance_km": 13245,
    "direction": "⬅️"
  },
  "KN": {
    "country": "Saint Kitts and Nevis",
    "distance_km": 13254,
    "direction": "⬅️"
  },
  "LC": {
    "country": "Saint Lucia",
    "distance_km": 13438,
    "direction": "⬅️"
  },
  "MF": {
    "country": "Saint Martin",
    "distance_km": 13220,
    "direction": "⬅️"
  },
  "PM": {
    "country": "Saint Pierre and Miquelon",
    "distance_km": 13271,
    "direction": "⬅️"
  },
  "VC": {
    "country": "Saint Vincent and the Grenadines",
    "distance_km": 13412,
    "direction": "⬅️"
  },
  "SX": {
    "country": "Sint Maarten",
    "distance_km": 13220,
    "direction": "⬅️"
  },
  "SR": {
    "country": "Suriname",
    "distance_km": 13913,
    "direction": "⬅️"
  },
  "TT": {
    "country": "Trinidad and Tobago",
    "distance_km": 13376,
    "direction": "⬅️"
  },
  "TC": {
    "country": "Turks and Caicos Islands",
    "distance_km": 12317,
    "direction": "⬅️"
  },
  "VI": {
    "country": "US Virgin Islands",
    "distance_km": 13041,
    "direction": "⬅️"
  },
  "VE": {
    "country": "Venezuela",
    "distance_km": 12798,
    "direction": "⬅️"
  },
  "BF": {
    "country": "Burkina Faso",
    "distance_km": 19603,
    "direction": "⬆️"
  },
  "CV": {
    "country": "Cabo Verde",
    "distance_km": 17425,
    "direction": "⬅️"
  },
  "CI": {
    "country": "Côte d'Ivoire",
    "distance_km": 19477,
    "direction": "⬅️"
  },
  "GM": {
    "country": "Gambia",
    "distance_km": 18331,
    "direction": "⬅️"
  },
  "GH": {
    "country": "Ghana",
    "distance_km": 19936,
    "direction": "↙️"
  },
  "GI": {
    "country": "Gibraltar",
    "distance_km": 16909,
    "direction": "⬆️"
  },
  "GN": {
    "country": "Guinea",
    "distance_km": 18879,
    "direction": "⬅️"
  },
  "GW": {
    "country": "Guinea-Bissau",
    "distance_km": 18415,
    "direction": "⬅️"
  },
  "LR": {
    "country": "Liberia",
    "distance_km": 19055,
    "direction": "⬅️"
  },
  "ML": {
    "country": "Mali",
    "distance_km": 18978,
    "direction": "⬆️"
  },
  "MR": {
    "country": "Mauritania",
    "distance_km": 18325,
    "direction": "↖️"
  },
  "MA": {
    "country": "Morocco",
    "distance_km": 17620,
    "direction": "⬆️"
  },
  "PT": {
    "country": "Portugal",
    "distance_km": 16478,
    "direction": "⬆️"
  },
  "SN": {
    "country": "Senegal",
    "distance_km": 18380,
    "direction": "⬅️"
  },
  "SL": {
    "country": "Sierra Leone",
    "distance_km": 18805,
    "direction": "⬅️"
  },
  "GL": {
    "country": "Greenland",
    "distance_km": 12253,
    "direction": "↖️"
  },
  "GG": {
    "country": "Guernsey",
    "distance_km": 15459,
    "direction": "⬆️"
  },
  "IE": {
    "country": "Ireland",
    "distance_km": 14990,
    "direction": "⬆️"
  },
  "IM": {
    "country": "Isle of Man",
    "distance_km": 14921,
    "direction": "⬆️"
  },
  "JE": {
    "country": "Jersey",
    "distance_km": 15488,
    "direction": "⬆️"
  },
  "GB": {
    "country": "United Kingdom",
    "distance_km": 14956,
    "direction": "⬆️"
  },
  "IS": {
    "country": "Iceland",
    "distance_km": 13562,
    "direction": "⬆️"
  },
  "FO": {
    "country": "Faroe Islands",
    "distance_km": 14032,
    "direction": "⬆️"
  },
  "SJ": {
    "country": "Svalbard",
    "distance_km": 12168,
    "direction": "⬆️"
  },
  "BV": {
    "country": "Bouvet Island",
    "distance_km": 13006,
    "direction": "⬇️"
  },
  "NZ": {
    "country": "New Zealand",
    "distance_km": 4013,
    "direction": "⬆️"
  },
  "AO": {
    "country": "Angola",
    "distance_km": 16943,
    "direction": "↘️"
  },
  "BW": {
    "country": "Botswana",
    "distance_km": 15667,
    "direction": "↘️"
  },
  "BI": {
    "country": "Burundi",
    "distance_km": 16371,
    "direction": "➡️"
  },
  "KM": {
    "country": "Comoros",
    "distance_km": 14645,
    "direction": "↘️"
  },
  "CG": {
    "country": "Congo",
    "distance_km": 17998,
    "direction": "↘️"
  },
  "CD": {
    "country": "Congo DRC",
    "distance_km": 17025,
    "direction": "↘️"
  },
  "GA": {
    "country": "Gabon",
    "distance_km": 18286,
    "direction": "↘️"
  },
  "KE": {
    "country": "Kenya",
    "distance_km": 15638,
    "direction": "➡️"
  },
  "LS": {
    "country": "Lesotho",
    "distance_km": 14761,
    "direction": "↘️"
  },
  "MW": {
    "country": "Malawi",
    "distance_km": 15460,
    "direction": "↘️"
  },
  "TF": {
    "country": "Glorioso Islands",
    "distance_km": 14250,
    "direction": "➡️"
  },
  "MZ": {
    "country": "Mozambique",
    "distance_km": 15115,
    "direction": "↘️"
  },
  "NA": {
    "country": "Namibia",
    "distance_km": 16051,
    "direction": "↘️"
  },
  "RW": {
    "country": "Rwanda",
    "distance_km": 16416,
    "direction": "➡️"
  },
  "ST": {
    "country": "Sao Tome and Principe",
    "distance_km": 18783,
    "direction": "↘️"
  },
  "ZA": {
    "country": "South Africa",
    "distance_km": 15065,
    "direction": "↘️"
  },
  "SZ": {
    "country": "Eswatini",
    "distance_km": 14785,
    "direction": "↘️"
  },
  "TZ": {
    "country": "Tanzania",
    "distance_km": 15736,
    "direction": "➡️"
  },
  "ZM": {
    "country": "Zambia",
    "distance_km": 16048,
    "direction": "↘️"
  },
  "ZW": {
    "country": "Zimbabwe",
    "distance_km": 15488,
    "direction": "↘️"
  },
  "IO": {
    "country": "British Indian Ocean Territory",
    "distance_km": 11712,
    "direction": "➡️"
  },
  "HM": {
    "country": "Heard Island and McDonald Islands",
    "distance_km": 10279,
    "direction": "➡️"
  },
  "MG": {
    "country": "Madagascar",
    "distance_km": 13978,
    "direction": "↘️"
  },
  "MU": {
    "country": "Mauritius",
    "distance_km": 12878,
    "direction": "➡️"
  },
  "YT": {
    "country": "Mayotte",
    "distance_km": 14416,
    "direction": "↘️"
  },
  "RE": {
    "country": "Réunion",
    "distance_km": 13040,
    "direction": "➡️"
  },
  "SC": {
    "country": "Seychelles",
    "distance_km": 13608,
    "direction": "➡️"
  },
  "DZ": {
    "country": "Algeria",
    "distance_km": 17780,
    "direction": "⬆️"
  },
  "BJ": {
    "country": "Benin",
    "distance_km": 19659,
    "direction": "➡️"
  },
  "CM": {
    "country": "Cameroon",
    "distance_km": 18481,
    "direction": "➡️"
  },
  "CF": {
    "country": "Central African Republic",
    "distance_km": 17654,
    "direction": "➡️"
  },
  "TD": {
    "country": "Chad",
    "distance_km": 17795,
    "direction": "➡️"
  },
  "GQ": {
    "country": "Equatorial Guinea",
    "distance_km": 18555,
    "direction": "↘️"
  },
  "KI": {
    "country": "Kiribati",
    "distance_km": 2838,
    "direction": "↙️"
  },
  "LY": {
    "country": "Libya",
    "distance_km": 17154,
    "direction": "↗️"
  },
  "MT": {
    "country": "Malta",
    "distance_km": 16602,
    "direction": "↗️"
  },
  "NE": {
    "country": "Niger",
    "distance_km": 18601,
    "direction": "↗️"
  },
  "NG": {
    "country": "Nigeria",
    "distance_km": 19027,
    "direction": "➡️"
  },
  "TG": {
    "country": "Togo",
    "distance_km": 19830,
    "direction": "➡️"
  },
  "TN": {
    "country": "Tunisia",
    "distance_km": 16978,
    "direction": "↗️"
  },
  "CY": {
    "country": "Cyprus",
    "distance_km": 15455,
    "direction": "↗️"
  },
  "DJ": {
    "country": "Djibouti",
    "distance_km": 15256,
    "direction": "➡️"
  },
  "EG": {
    "country": "Egypt",
    "distance_km": 16178,
    "direction": "↗️"
  },
  "ER": {
    "country": "Eritrea",
    "distance_km": 15602,
    "direction": "➡️"
  },
  "ET": {
    "country": "Ethiopia",
    "distance_km": 15543,
    "direction": "➡️"
  },
  "GR": {
    "country": "Greece",
    "distance_km": 15837,
    "direction": "↗️"
  },
  "IQ": {
    "country": "Iraq",
    "distance_km": 14690,
    "direction": "➡️"
  },
  "IL": {
    "country": "Israel",
    "distance_km": 15519,
    "direction": "↗️"
  },
  "JO": {
    "country": "Jordan",
    "distance_km": 15360,
    "direction": "↗️"
  },
  "LB": {
    "country": "Lebanon",
    "distance_km": 15323,
    "direction": "↗️"
  },
  "PS": {
    "country": "Palestinian Territory",
    "distance_km": 15480,
    "direction": "↗️"
  },
  "SS": {
    "country": "South Sudan",
    "distance_km": 16583,
    "direction": "➡️"
  },
  "SD": {
    "country": "Sudan",
    "distance_km": 16584,
    "direction": "➡️"
  },
  "SY": {
    "country": "Syria",
    "distance_km": 15050,
    "direction": "↗️"
  },
  "TR": {
    "country": "Turkey",
    "distance_km": 15061,
    "direction": "↗️"
  },
  "UG": {
    "country": "Uganda",
    "distance_km": 16261,
    "direction": "➡️"
  },
  "AD": {
    "country": "Andorra",
    "distance_km": 16224,
    "direction": "⬆️"
  },
  "US": {
    "country": "United States",
    "distance_km": 10124,
    "direction": "⬅️"
  },
  "FR": {
    "country": "France",
    "distance_km": 15766,
    "direction": "⬆️"
  },
  "LI": {
    "country": "Liechtenstein",
    "distance_km": 15609,
    "direction": "⬆️"
  },
  "MC": {
    "country": "Monaco",
    "distance_km": 16017,
    "direction": "⬆️"
  },
  "CH": {
    "country": "Switzerland",
    "distance_km": 15678,
    "direction": "⬆️"
  },
  "BE": {
    "country": "Belgium",
    "distance_km": 15306,
    "direction": "⬆️"
  },
  "DE": {
    "country": "Germany",
    "distance_km": 15171,
    "direction": "⬆️"
  },
  "LU": {
    "country": "Luxembourg",
    "distance_km": 15383,
    "direction": "⬆️"
  },
  "NL": {
    "country": "Netherlands",
    "distance_km": 15131,
    "direction": "⬆️"
  },
  "AL": {
    "country": "Albania",
    "distance_km": 15846,
    "direction": "↗️"
  },
  "AT": {
    "country": "Austria",
    "distance_km": 15453,
    "direction": "⬆️"
  },
  "BA": {
    "country": "Bosnia and Herzegovina",
    "distance_km": 15664,
    "direction": "↗️"
  },
  "HR": {
    "country": "Croatia",
    "distance_km": 15635,
    "direction": "↗️"
  },
  "CZ": {
    "country": "Czech Republic",
    "distance_km": 15191,
    "direction": "↗️"
  },
  "DK": {
    "country": "Denmark",
    "distance_km": 14660,
    "direction": "⬆️"
  },
  "HU": {
    "country": "Hungary",
    "distance_km": 15306,
    "direction": "↗️"
  },
  "IT": {
    "country": "Italy",
    "distance_km": 15961,
    "direction": "↗️"
  },
  "ME": {
    "country": "Montenegro",
    "distance_km": 15735,
    "direction": "↗️"
  },
  "PL": {
    "country": "Poland",
    "distance_km": 14835,
    "direction": "↗️"
  },
  "SM": {
    "country": "San Marino",
    "distance_km": 15872,
    "direction": "⬆️"
  },
  "RS": {
    "country": "Serbia",
    "distance_km": 15546,
    "direction": "↗️"
  },
  "SK": {
    "country": "Slovakia",
    "distance_km": 15158,
    "direction": "↗️"
  },
  "SI": {
    "country": "Slovenia",
    "distance_km": 15572,
    "direction": "↗️"
  },
  "MK": {
    "country": "North Macedonia",
    "distance_km": 15724,
    "direction": "↗️"
  },
  "VA": {
    "country": "Vatican City",
    "distance_km": 16082,
    "direction": "↗️"
  },
  "NO": {
    "country": "Norway",
    "distance_km": 13591,
    "direction": "⬆️"
  },
  "SE": {
    "country": "Sweden",
    "distance_km": 13817,
    "direction": "⬆️"
  },
  "BY": {
    "country": "Belarus",
    "distance_km": 14392,
    "direction": "↗️"
  },
  "BG": {
    "country": "Bulgaria",
    "distance_km": 15434,
    "direction": "↗️"
  },
  "EE": {
    "country": "Estonia",
    "distance_km": 13998,
    "direction": "↗️"
  },
  "FI": {
    "country": "Finland",
    "distance_km": 13404,
    "direction": "↗️"
  },
  "GE": {
    "country": "Georgia",
    "distance_km": 14310,
    "direction": "↗️"
  },
  "LV": {
    "country": "Latvia",
    "distance_km": 14208,
    "direction": "↗️"
  },
  "LT": {
    "country": "Lithuania",
    "distance_km": 14376,
    "direction": "↗️"
  },
  "MD": {
    "country": "Moldova",
    "distance_km": 14917,
    "direction": "↗️"
  },
  "RO": {
    "country": "Romania",
    "distance_km": 15186,
    "direction": "↗️"
  },
  "UA": {
    "country": "Ukraine",
    "distance_km": 14641,
    "direction": "↗️"
  },
  "AF": {
    "country": "Afghanistan",
    "distance_km": 12615,
    "direction": "➡️"
  },
  "BH": {
    "country": "Bahrain",
    "distance_km": 14270,
    "direction": "➡️"
  },
  "IN": {
    "country": "India",
    "distance_km": 11200,
    "direction": "➡️"
  },
  "IR": {
    "country": "Iran",
    "distance_km": 13767,
    "direction": "➡️"
  },
  "KW": {
    "country": "Kuwait",
    "distance_km": 14480,
    "direction": "➡️"
  },
  "MV": {
    "country": "Maldives",
    "distance_km": 11769,
    "direction": "➡️"
  },
  "NP": {
    "country": "Nepal",
    "distance_km": 10950,
    "direction": "➡️"
  },
  "OM": {
    "country": "Oman",
    "distance_km": 13804,
    "direction": "➡️"
  },
  "PK": {
    "country": "Pakistan",
    "distance_km": 12413,
    "direction": "➡️"
  },
  "QA": {
    "country": "Qatar",
    "distance_km": 14219,
    "direction": "➡️"
  },
  "SA": {
    "country": "Saudi Arabia",
    "distance_km": 14898,
    "direction": "➡️"
  },
  "SO": {
    "country": "Somalia",
    "distance_km": 14922,
    "direction": "➡️"
  },
  "LK": {
    "country": "Sri Lanka",
    "distance_km": 11067,
    "direction": "➡️"
  },
  "TJ": {
    "country": "Tajikistan",
    "distance_km": 12182,
    "direction": "➡️"
  },
  "TM": {
    "country": "Turkmenistan",
    "distance_km": 13241,
    "direction": "➡️"
  },
  "AE": {
    "country": "United Arab Emirates",
    "distance_km": 13929,
    "direction": "➡️"
  },
  "YE": {
    "country": "Yemen",
    "distance_km": 14718,
    "direction": "➡️"
  },
  "AM": {
    "country": "Armenia",
    "distance_km": 14284,
    "direction": "↗️"
  },
  "AZ": {
    "country": "Azerbaijan",
    "distance_km": 13996,
    "direction": "➡️"
  },
  "KZ": {
    "country": "Kazakhstan",
    "distance_km": 12409,
    "direction": "➡️"
  },
  "KG": {
    "country": "Kyrgyzstan",
    "distance_km": 11885,
    "direction": "➡️"
  },
  "UZ": {
    "country": "Uzbekistan",
    "distance_km": 12737,
    "direction": "➡️"
  },
  "CX": {
    "country": "Christmas Island",
    "distance_km": 8048,
    "direction": "➡️"
  },
  "CC": {
    "country": "Cocos Islands",
    "distance_km": 8988,
    "direction": "➡️"
  },
  "ID": {
    "country": "Indonesia",
    "distance_km": 7291,
    "direction": "➡️"
  },
  "TL": {
    "country": "Timor-Leste",
    "distance_km": 5850,
    "direction": "➡️"
  },
  "AU": {
    "country": "Australia",
    "distance_km": 5137,
    "direction": "➡️"
  },
  "NR": {
    "country": "Nauru",
    "distance_km": 1625,
    "direction": "↘️"
  },
  "NC": {
    "country": "New Caledonia",
    "distance_km": 2047,
    "direction": "↗️"
  },
  "NF": {
    "country": "Norfolk Island",
    "distance_km": 2568,
    "direction": "↗️"
  },
  "PG": {
    "country": "Papua New Guinea",
    "distance_km": 3789,
    "direction": "➡️"
  },
  "SB": {
    "country": "Solomon Islands",
    "distance_km": 2095,
    "direction": "➡️"
  },
  "VU": {
    "country": "Vanuatu",
    "distance_km": 1536,
    "direction": "↗️"
  },
  "KH": {
    "country": "Cambodia",
    "distance_km": 8526,
    "direction": "➡️"
  },
  "LA": {
    "country": "Laos",
    "distance_km": 8789,
    "direction": "➡️"
  },
  "MY": {
    "country": "Malaysia",
    "distance_km": 7287,
    "direction": "➡️"
  },
  "MM": {
    "country": "Myanmar",
    "distance_km": 9517,
    "direction": "➡️"
  },
  "SG": {
    "country": "Singapore",
    "distance_km": 8427,
    "direction": "➡️"
  },
  "TH": {
    "country": "Thailand",
    "distance_km": 8966,
    "direction": "➡️"
  },
  "VN": {
    "country": "Vietnam",
    "distance_km": 8527,
    "direction": "➡️"
  },
  "BD": {
    "country": "Bangladesh",
    "distance_km": 10264,
    "direction": "➡️"
  },
  "BT": {
    "country": "Bhutan",
    "distance_km": 10320,
    "direction": "➡️"
  },
  "CN": {
    "country": "China",
    "distance_km": 9264,
    "direction": "➡️"
  },
  "BN": {
    "country": "Brunei Darussalam",
    "distance_km": 7305,
    "direction": "➡️"
  },
  "PH": {
    "country": "Philippines",
    "distance_km": 6865,
    "direction": "➡️"
  },
  "KR": {
    "country": "South Korea",
    "distance_km": 7329,
    "direction": "↘️"
  },
  "MN": {
    "country": "Mongolia",
    "distance_km": 9647,
    "direction": "➡️"
  },
  "KP": {
    "country": "North Korea",
    "distance_km": 7587,
    "direction": "↘️"
  },
  "GU": {
    "country": "Guam",
    "distance_km": 4518,
    "direction": "↘️"
  },
  "JP": {
    "country": "Japan",
    "distance_km": 6654,
    "direction": "↘️"
  },
  "MH": {
    "country": "Marshall Islands",
    "distance_km": 2109,
    "direction": "↘️"
  },
  "FM": {
    "country": "Micronesia",
    "distance_km": 2888,
    "direction": "↘️"
  },
  "MP": {
    "country": "Northern Mariana Islands",
    "distance_km": 4533,
    "direction": "↘️"
  },
  "PW": {
    "country": "Palau",
    "distance_km": 5259,
    "direction": "➡️"
  },
  "RU": {
    "country": "Russian Federation",
    "distance_km": 10284,
    "direction": "➡️"
  },
  "ES": {
    "country": "Canarias",
    "distance_km": 17265,
    "direction": "↖️"
  }
}